{"/zh-cn/about/":{"data":{"":"","致谢#致谢":"我们的愿景是打造在 Windows 和 Xbox 平台上最佳的原生应用体验，采用最新的平台技术。\n通过以下方式支持这些项目：\n将应用分享给社区 购买专业版 在商店中留下五星好评。 为了跟踪应用开发的最新动态，我们即将开设一个公告频道。\n致谢\r这些应用的开发离不开以下工具和灵感来源：\nJson.NET WinUI 2.8 Windows Community Toolkit LibVLCSharp FFmpeg Html2Markdown Hugo "},"title":"关于"},"/zh-cn/blog/":{"data":{"":"\rRSS 订阅 "},"title":"博客"},"/zh-cn/docs/":{"data":{"":"","下一步#下一步":"👋 你好！欢迎来到 JimmyRespawn 文档！\n什么是 JimmyRespawn？\rJimmyRespawn 是一家软件发行商，致力于为 Windows 和 Xbox 平台提供高质量的原生应用程序，利用微软的最新技术提升用户体验。\n功能特色\r精美设计 - 受到 Fluent 设计指南的启发，提供现代化的设计，使应用外观出众。 响应式布局与暗模式 - 无论是在 Xbox、平板电脑还是桌面设备上，都能展现出色的视觉效果。同时支持暗模式，以适应不同的光照环境。 快速轻便 - 由 UWP 驱动，这是一种基于 .Net native 构建的超快速软件基础架构，JimmyRespawn 保持其占用空间最小化。使用时无需额外的 EXE 安装。 有问题或反馈？\r❓\rJimmyRespawn 的应用仍在积极开发中。 有问题或反馈？请随时 提交问题！\r下一步\r立即进入以下部分开始：\n入门指南了解如何使用商店下载应用","什么是-jimmyrespawn#什么是 JimmyRespawn？":"","功能特色#功能特色":"","有问题或反馈#有问题或反馈？":""},"title":"文档"},"/zh-cn/showcase/":{"data":{"":"\r由 JimmyRespawn 发行的应用。\r钉笔记\r字数统计\rStage1st\rTGFC"},"title":"项目展示"}}